pymovements/__init__.py
pymovements/_version.py
pymovements/exceptions.py
pymovements/_scripts/__init__.py
pymovements/_scripts/write_dataset_docpages.py
pymovements/_scripts/write_datasets_yaml.py
pymovements/_utils/__init__.py
pymovements/_utils/_checks.py
pymovements/_utils/_deprecated.py
pymovements/_utils/_html.py
pymovements/_utils/_paths.py
pymovements/_utils/_strings.py
pymovements/dataset/__init__.py
pymovements/dataset/dataset.py
pymovements/dataset/dataset_definition.py
pymovements/dataset/dataset_download.py
pymovements/dataset/dataset_files.py
pymovements/dataset/dataset_library.py
pymovements/dataset/dataset_paths.py
pymovements/dataset/resources.py
pymovements/dataset/_utils/__init__.py
pymovements/dataset/_utils/_archives.py
pymovements/dataset/_utils/_downloads.py
pymovements/dataset/_utils/_yaml.py
pymovements/datasets/__init__.py
pymovements/datasets/bsc.py
pymovements/datasets/bsc.yaml
pymovements/datasets/bsc2.py
pymovements/datasets/bsc2.yaml
pymovements/datasets/chinese_reading.py
pymovements/datasets/chinese_reading.yaml
pymovements/datasets/codecomprehension.py
pymovements/datasets/codecomprehension.yaml
pymovements/datasets/colagaze.py
pymovements/datasets/colagaze.yaml
pymovements/datasets/copco.py
pymovements/datasets/copco.yaml
pymovements/datasets/daemons.py
pymovements/datasets/daemons.yaml
pymovements/datasets/datasets.yaml
pymovements/datasets/didec.py
pymovements/datasets/didec.yaml
pymovements/datasets/emtec.py
pymovements/datasets/emtec.yaml
pymovements/datasets/etdd70.py
pymovements/datasets/etdd70.yaml
pymovements/datasets/fakenews.py
pymovements/datasets/fakenews.yaml
pymovements/datasets/gaze4hate.py
pymovements/datasets/gaze4hate.yaml
pymovements/datasets/gaze_graph.py
pymovements/datasets/gaze_graph.yaml
pymovements/datasets/gaze_on_faces.py
pymovements/datasets/gaze_on_faces.yaml
pymovements/datasets/gazebase.py
pymovements/datasets/gazebase.yaml
pymovements/datasets/gazebasevr.py
pymovements/datasets/gazebasevr.yaml
pymovements-0.24.1.dist-info/licenses/LICENSE.txt
pymovements-0.24.1.dist-info/METADATA
pymovements-0.24.1.dist-info/WHEEL
pymovements-0.24.1.dist-info/top_level.txt
pymovements-0.24.1.dist-info/RECORD
