Metadata-Version: 2.4
Name: pymovements
Version: 0.24.1
Summary: A python package for processing eye movement data
Maintainer-email: Daniel Krakowczyk <daniel.krakowczyk@uni-potsdam.de>
License-Expression: MIT
Project-URL: Homepage, https://github.com/pymovements/pymovements
Project-URL: Source Code, https://github.com/pymovements/pymovements
Project-URL: Documentation, https://pymovements.readthedocs.io/en/stable
Project-URL: Bug Tracker, https://github.com/pymovements/pymovements/issues
Project-URL: Changelog, https://github.com/pymovements/pymovements/releases
Classifier: Development Status :: 4 - Beta
Classifier: Intended Audience :: Science/Research
Classifier: Operating System :: MacOS :: MacOS X
Classifier: Operating System :: Microsoft :: Windows
Classifier: Operating System :: POSIX :: Linux
Classifier: Operating System :: OS Independent
Classifier: Programming Language :: Python :: 3.9
Classifier: Programming Language :: Python :: 3.10
Classifier: Programming Language :: Python :: 3.11
Classifier: Programming Language :: Python :: 3.12
Classifier: Programming Language :: Python :: 3.13
Classifier: Topic :: Scientific/Engineering
Classifier: Typing :: Typed
Requires-Python: >=3.9
License-File: LICENSE.txt
Requires-Dist: deprecated<1.4,>=1.2.18
Requires-Dist: matplotlib<3.11,>=3.8.0
Requires-Dist: fastexcel<1.0,>=0.13.0
Requires-Dist: numpy<2.3,>=1.22.4
Requires-Dist: pandas<2.4,>=2.1.4
Requires-Dist: polars<1.32,>=1.31.0
Requires-Dist: pyarrow<21.1,>=11.0.0
Requires-Dist: pyopenssl<25.4,>=16.0.0
Requires-Dist: pyreadr<0.6,>=0.5.2
Requires-Dist: pyyaml<6.1,>=6.0.2
Requires-Dist: scipy<1.16,>=1.8.0
Requires-Dist: tqdm<4.68,>=4.27.0
Requires-Dist: typing_extensions<4.16,>=4.0.0
Provides-Extra: docs
Requires-Dist: ipykernel<6.32,>=6.13.0; extra == "docs"
Requires-Dist: ipywidgets<8.2,>=8.1.7; extra == "docs"
Requires-Dist: myst-nb>=1.0.0; extra == "docs"
Requires-Dist: nbconvert<7.17,>=7.0.0; extra == "docs"
Requires-Dist: pandoc; extra == "docs"
Requires-Dist: pybtex<0.25.2; extra == "docs"
Requires-Dist: pydata-sphinx-theme>=0.12; extra == "docs"
Requires-Dist: setuptools<81,>=61.0.0; extra == "docs"
Requires-Dist: sphinx<8.3,>=7.0; extra == "docs"
Requires-Dist: sphinx-copybutton>=0.4.0; extra == "docs"
Requires-Dist: sphinx-favicon>=1.0.1; extra == "docs"
Requires-Dist: sphinx_design>=0.3.0; extra == "docs"
Requires-Dist: sphinx_mdinclude>=0.5.0; extra == "docs"
Requires-Dist: sphinxcontrib.datatemplates>=0.9.0; extra == "docs"
Requires-Dist: sphinxcontrib.bibtex>=2.4.1; extra == "docs"
Provides-Extra: dev
Requires-Dist: tox<4.31,>=4.12.0; extra == "dev"
Requires-Dist: pybtex<0.25.2; extra == "dev"
Requires-Dist: pytest>=7.0.0; extra == "dev"
Requires-Dist: pytest-benchmark>=5.1.0; extra == "dev"
Requires-Dist: pytest-cov>=4.0.0; extra == "dev"
Requires-Dist: setuptools<81,>=61.0.0; extra == "dev"
Requires-Dist: types-tqdm<5,>=4.64.0; extra == "dev"
Requires-Dist: pre-commit<4.4.0,>=3.0.0; extra == "dev"
Requires-Dist: pylint<3.4,>=2.0.0; extra == "dev"
Dynamic: license-file
